LICENSE
MANIFEST.in
README.md
setup.py
./requirements.txt
kot_secret/__init__.py
kot_secret/kot_secret.py
kot_secret.egg-info/PKG-INFO
kot_secret.egg-info/SOURCES.txt
kot_secret.egg-info/dependency_links.txt
kot_secret.egg-info/not-zip-safe
kot_secret.egg-info/requires.txt
kot_secret.egg-info/top_level.txt