Metadata-Version: 2.1
Name: kot-secret
Version: 0.1.0
Summary: The cloud secret save system for your python applications !
Home-page: https://github.com/KOT-database/KOT-Secret
License: MIT
Platform: UNKNOWN
Requires-Python: >= 3
